topsis/__init__.py
TOPSIS_parteekpal_101803190-0.3.dist-info/LICENSE.txt
TOPSIS_parteekpal_101803190-0.3.dist-info/METADATA
TOPSIS_parteekpal_101803190-0.3.dist-info/WHEEL
TOPSIS_parteekpal_101803190-0.3.dist-info/top_level.txt
TOPSIS_parteekpal_101803190-0.3.dist-info/RECORD
